LICENSE
MANIFEST.in
README.md
setup.py
bigstate/__init__.py
bigstate/ltm.py
bigstate/net.py
bigstate.egg-info/PKG-INFO
bigstate.egg-info/SOURCES.txt
bigstate.egg-info/dependency_links.txt
bigstate.egg-info/requires.txt
bigstate.egg-info/top_level.txt