Metadata-Version: 1.1
Name: bigstate
Version: 0.0.1
Summary: state modules for f5 bigips
Home-page: https://github.com/brokenbot/bigstate
Author: David Sanderson
Author-email: dave.d.sanderson@gmail.com
License: UNKNOWN
Keywords: salt f5 bigip ltm
Platform: UNKNOWN
Classifier: Development Status :: 3 - Alpha
Classifier: Intended Audience :: Developers
Classifier: License :: OSI Approved :: BSD License
Classifier: Programming Language :: Python :: 3
